[{"province_code":"u","name":"28 De Julio"},{"province_code":"u","name":"Aguada De Las Tejas"},{"province_code":"u","name":"Aguada Del Pito"},{"province_code":"u","name":"Aldea Apeleg"},{"province_code":"u","name":"Aldea Beleiro"},{"province_code":"u","name":"Aldea Escolar"},{"province_code":"u","name":"Alto De Las Plumas"},{"province_code":"u","name":"Alto Rio Mayo"},{"province_code":"u","name":"Alto Rio Pico"},{"province_code":"u","name":"Alto Rio Senguer"},{"province_code":"u","name":"Angostura"},{"province_code":"u","name":"Angostura Segunda"},{"province_code":"u","name":"Arenoso"},{"province_code":"u","name":"Arroyo Chalia"},{"province_code":"u","name":"Arroyo Gato"},{"province_code":"u","name":"Arroyo Guilaia"},{"province_code":"u","name":"Arroyo Percy"},{"province_code":"u","name":"Arroyo Pescado"},{"province_code":"u","name":"Arroyo Quilla"},{"province_code":"u","name":"Arroyo Verde"},{"province_code":"u","name":"Bahia Bustamante"},{"province_code":"u","name":"Bahia Cracher"},{"province_code":"u","name":"Bahia Solano"},{"province_code":"u","name":"Bajada Del Diablo"},{"province_code":"u","name":"Bajada Moreno"},{"province_code":"u","name":"Bajo Bartolo"},{"province_code":"u","name":"Bajo Del Gualicho"},{"province_code":"u","name":"Bajo De Los Huesos"},{"province_code":"u","name":"Bajo La Cancha"},{"province_code":"u","name":"Bajo Las Damajuanas"},{"province_code":"u","name":"Barrio Astra"},{"province_code":"u","name":"Base Aeronaval Almirante Zar"},{"province_code":"u","name":"Betesta"},{"province_code":"u","name":"Boca De La Zanja"},{"province_code":"u","name":"Boca Zanja Sud"},{"province_code":"u","name":"Bryn Brown"},{"province_code":"u","name":"Bryn Gwyn"},{"province_code":"u","name":"Buenos Aires Chico"},{"province_code":"u","name":"Buen Pasto"},{"province_code":"u","name":"Cabana Del Valle"},{"province_code":"u","name":"Cabeza De Buey"},{"province_code":"u","name":"Cabo Raso"},{"province_code":"u","name":"Cachel"},{"province_code":"u","name":"Cajon De Ginebra Chico"},{"province_code":"u","name":"Cajon De Ginebra Grande"},{"province_code":"u","name":"Caleta Cordova"},{"province_code":"u","name":"Caleta Valdez"},{"province_code":"u","name":"Camarones"},{"province_code":"u","name":"Campamento Villegas"},{"province_code":"u","name":"Canada Bagual"},{"province_code":"u","name":"Canadon Bagual"},{"province_code":"u","name":"Canadon Blanco"},{"province_code":"u","name":"Canadon Caliente"},{"province_code":"u","name":"Canadon Carril"},{"province_code":"u","name":"Canadon Chacay"},{"province_code":"u","name":"Canadon Chileno"},{"province_code":"u","name":"Canadon Ferrais"},{"province_code":"u","name":"Canadon Grande"},{"province_code":"u","name":"Canadon Lagarto"},{"province_code":"u","name":"Canadon La Madera"},{"province_code":"u","name":"Canadon Lopez"},{"province_code":"u","name":"Canadon Pedro Ex Valle Hermoso"},{"province_code":"u","name":"Canadon Tacho"},{"province_code":"u","name":"Carhue Niyeo"},{"province_code":"u","name":"Carrenleufu"},{"province_code":"u","name":"Casa Blanca"},{"province_code":"u","name":"Cataico"},{"province_code":"u","name":"Cerro Centinela"},{"province_code":"u","name":"Cerro Condor"},{"province_code":"u","name":"Cerro Fofocahuel"},{"province_code":"u","name":"Cerro Lonco Trapial"},{"province_code":"u","name":"Cerro Mallaco"},{"province_code":"u","name":"Cerro Negro"},{"province_code":"u","name":"Cerro Pichalao"},{"province_code":"u","name":"Cerro Radal"},{"province_code":"u","name":"Cerro Santa Ana"},{"province_code":"u","name":"Chacay Este"},{"province_code":"u","name":"Chacay Oeste"},{"province_code":"u","name":"Chacra De Austin"},{"province_code":"u","name":"Charque Chico"},{"province_code":"u","name":"Chasico"},{"province_code":"u","name":"Cholila"},{"province_code":"u","name":"Colanconhue"},{"province_code":"u","name":"Colelache"},{"province_code":"u","name":"Colhue Huapi"},{"province_code":"u","name":"Colonia 16 De Octubre"},{"province_code":"u","name":"Colonia Cushamen"},{"province_code":"u","name":"Colonia Epulief"},{"province_code":"u","name":"Colonia Germania"},{"province_code":"u","name":"Comodoro Rivadavia"},{"province_code":"u","name":"Corcovado"},{"province_code":"u","name":"Corralitos"},{"province_code":"u","name":"Costa Chubut"},{"province_code":"u","name":"Costa Del Lepa"},{"province_code":"u","name":"Costa Rio Chico"},{"province_code":"u","name":"Cushamen"},{"province_code":"u","name":"Dique Florentino Ameghino"},{"province_code":"u","name":"Doctor Ricardo Rojas"},{"province_code":"u","name":"Dolavon"},{"province_code":"u","name":"Dos Pozos"},{"province_code":"u","name":"Ebenecer"},{"province_code":"u","name":"El Alamo"},{"province_code":"u","name":"El Argentino"},{"province_code":"u","name":"El Boquete"},{"province_code":"u","name":"El Cajon"},{"province_code":"u","name":"El Calafate"},{"province_code":"u","name":"El Canquel"},{"province_code":"u","name":"El Chacay Dpto Gastre"},{"province_code":"u","name":"El Chalet"},{"province_code":"u","name":"El Cherque"},{"province_code":"u","name":"El Coihue"},{"province_code":"u","name":"El Coyte"},{"province_code":"u","name":"El Cronometro"},{"province_code":"u","name":"El Cuche"},{"province_code":"u","name":"El Desempeno"},{"province_code":"u","name":"El Escorial"},{"province_code":"u","name":"El Hoyo"},{"province_code":"u","name":"El Jaguel"},{"province_code":"u","name":"El Kaquel"},{"province_code":"u","name":"El Maiten"},{"province_code":"u","name":"El Mirador"},{"province_code":"u","name":"El Mirasol"},{"province_code":"u","name":"El Molle"},{"province_code":"u","name":"El Pajarito"},{"province_code":"u","name":"El Pastizal"},{"province_code":"u","name":"El Piquillin"},{"province_code":"u","name":"El Portezuelo"},{"province_code":"u","name":"El Porvenir"},{"province_code":"u","name":"El Poyo"},{"province_code":"u","name":"El Quilimuay"},{"province_code":"u","name":"El Ruano"},{"province_code":"u","name":"El Salitral"},{"province_code":"u","name":"El Shaman"},{"province_code":"u","name":"El Sombrero"},{"province_code":"u","name":"El Triana"},{"province_code":"u","name":"El Tropezon"},{"province_code":"u","name":"Empalme A Astra"},{"province_code":"u","name":"Empalme Puerto Lobos"},{"province_code":"u","name":"Enrique Hermitte"},{"province_code":"u","name":"Epuyen"},{"province_code":"u","name":"Esquel"},{"province_code":"u","name":"Estancia El Moro"},{"province_code":"u","name":"Estancia La Mimosa"},{"province_code":"u","name":"Estancia Pampa Chica"},{"province_code":"u","name":"Facundo"},{"province_code":"u","name":"Fithen Verin"},{"province_code":"u","name":"Fitirhuin"},{"province_code":"u","name":"Florentino Ameghino"},{"province_code":"u","name":"Fotocahuel"},{"province_code":"u","name":"Frontera De Rio Pico"},{"province_code":"u","name":"Futaleufu"},{"province_code":"u","name":"Gaiman"},{"province_code":"u","name":"Gan Gan"},{"province_code":"u","name":"Garayalde"},{"province_code":"u","name":"Gastre"},{"province_code":"u","name":"General Mosconi"},{"province_code":"u","name":"Glasfryn"},{"province_code":"u","name":"Gobernador Costa"},{"province_code":"u","name":"Gualjaina"},{"province_code":"u","name":"Hito 43"},{"province_code":"u","name":"Hito 45"},{"province_code":"u","name":"Hito 50"},{"province_code":"u","name":"Holdich"},{"province_code":"u","name":"Ing Bruno J Thomae"},{"province_code":"u","name":"Jose De San Martin"},{"province_code":"u","name":"La Bombilla"},{"province_code":"u","name":"La Cancha"},{"province_code":"u","name":"La Castellana"},{"province_code":"u","name":"La Corona"},{"province_code":"u","name":"Lago Blanco"},{"province_code":"u","name":"Lago Carlos Pellegrini"},{"province_code":"u","name":"Lago Fontana"},{"province_code":"u","name":"Lago Lezama"},{"province_code":"u","name":"Lago Musters"},{"province_code":"u","name":"Lago Paz"},{"province_code":"u","name":"Lago Puelo"},{"province_code":"u","name":"Lago Rivadavia"},{"province_code":"u","name":"Lago Rosario"},{"province_code":"u","name":"Lago Verde"},{"province_code":"u","name":"Lago Vintter"},{"province_code":"u","name":"Laguna Blanca"},{"province_code":"u","name":"Laguna Del Mate"},{"province_code":"u","name":"Laguna De Vacas"},{"province_code":"u","name":"Laguna Fria"},{"province_code":"u","name":"Laguna Grande"},{"province_code":"u","name":"Laguna Palacio"},{"province_code":"u","name":"Laguna Rincon Del Moro"},{"province_code":"u","name":"Laguna Terraplen"},{"province_code":"u","name":"Laguna Verde"},{"province_code":"u","name":"Lagunita Salada"},{"province_code":"u","name":"La Lancha"},{"province_code":"u","name":"La Laurita"},{"province_code":"u","name":"Languineo"},{"province_code":"u","name":"La Nicolasa"},{"province_code":"u","name":"La Pepita"},{"province_code":"u","name":"La Primavera"},{"province_code":"u","name":"La Rosilla"},{"province_code":"u","name":"Larralde"},{"province_code":"u","name":"La Salamanca"},{"province_code":"u","name":"Las Chapas"},{"province_code":"u","name":"Las Cortaderas"},{"province_code":"u","name":"Las Golondrinas"},{"province_code":"u","name":"Las Horquetas"},{"province_code":"u","name":"La Siberia"},{"province_code":"u","name":"Las Mulas"},{"province_code":"u","name":"Las Pampas"},{"province_code":"u","name":"Las Plumas"},{"province_code":"u","name":"Las Pulgas"},{"province_code":"u","name":"Las Salinas"},{"province_code":"u","name":"Legua 24"},{"province_code":"u","name":"Leleque"},{"province_code":"u","name":"Lenzanilleo"},{"province_code":"u","name":"Loma Redonda"},{"province_code":"u","name":"Loreto"},{"province_code":"u","name":"Los Altares"},{"province_code":"u","name":"Los Cipreses"},{"province_code":"u","name":"Los Corralitos"},{"province_code":"u","name":"Los Manantiales"},{"province_code":"u","name":"Los Tamariscos"},{"province_code":"u","name":"Maesteg"},{"province_code":"u","name":"Malaspina"},{"province_code":"u","name":"Mallin Blanco"},{"province_code":"u","name":"Mallin Grande"},{"province_code":"u","name":"Mallin Grande Corcovado"},{"province_code":"u","name":"Manantial Grande"},{"province_code":"u","name":"Mata Grande"},{"province_code":"u","name":"Matucana"},{"province_code":"u","name":"Mayoco"},{"province_code":"u","name":"Medanos"},{"province_code":"u","name":"Nahuel Pan Estacion Fcgr"},{"province_code":"u","name":"Niriguao"},{"province_code":"u","name":"Niriguce Pampa"},{"province_code":"u","name":"Norquinco Sud"},{"province_code":"u","name":"Nueva Lubecka"},{"province_code":"u","name":"Painaluf"},{"province_code":"u","name":"Pampa De Agnia"},{"province_code":"u","name":"Pampa Del Castillo"},{"province_code":"u","name":"Pampa Pelada"},{"province_code":"u","name":"Pampa Salamanca"},{"province_code":"u","name":"Pampa Tepuel"},{"province_code":"u","name":"Parque Nacional Los Alerces"},{"province_code":"u","name":"Paso De Indios"},{"province_code":"u","name":"Paso Del Sapo"},{"province_code":"u","name":"Paso De Torres"},{"province_code":"u","name":"Paso Moreno"},{"province_code":"u","name":"Pastos Blancos"},{"province_code":"u","name":"Pico Salamanca"},{"province_code":"u","name":"Piedra Parada"},{"province_code":"u","name":"Piedra Shotel"},{"province_code":"u","name":"Pirre Mahuida"},{"province_code":"u","name":"Plancuntre"},{"province_code":"u","name":"Playa Union"},{"province_code":"u","name":"Pocitos De Quichaura"},{"province_code":"u","name":"Puente Hendre"},{"province_code":"u","name":"Puerto Lobos"},{"province_code":"u","name":"Puerto Madryn"},{"province_code":"u","name":"Puerto Piramides"},{"province_code":"u","name":"Puerto San Roman"},{"province_code":"u","name":"Punta Bajos"},{"province_code":"u","name":"Punta Delgada"},{"province_code":"u","name":"Punta Ninfas"},{"province_code":"u","name":"Punta Norte"},{"province_code":"u","name":"Punta Quiroga"},{"province_code":"u","name":"Putrachoique"},{"province_code":"u","name":"Rada Tilly"},{"province_code":"u","name":"Ranquil Huao"},{"province_code":"u","name":"Rawson"},{"province_code":"u","name":"Rio Chico"},{"province_code":"u","name":"Rio Corinto"},{"province_code":"u","name":"Rio Frias"},{"province_code":"u","name":"Rio Mayo"},{"province_code":"u","name":"Rio Pico"},{"province_code":"u","name":"Sacanana"},{"province_code":"u","name":"Salinas Chicas"},{"province_code":"u","name":"Salinas Grandes"},{"province_code":"u","name":"San Jose"},{"province_code":"u","name":"Sarmiento"},{"province_code":"u","name":"Seprucal"},{"province_code":"u","name":"Siempre Viva"},{"province_code":"u","name":"Sierra Chata"},{"province_code":"u","name":"Sierra Chica"},{"province_code":"u","name":"Sierra Colorada"},{"province_code":"u","name":"Sierra Corrientes"},{"province_code":"u","name":"Sierra Cuadrada"},{"province_code":"u","name":"Sierra De Tecka"},{"province_code":"u","name":"Sierra Nevada Buen Pasto"},{"province_code":"u","name":"Sierra Nevada Paso De Indios"},{"province_code":"u","name":"Sierra Overa Chicas Y Grandes"},{"province_code":"u","name":"Sierra Rosada"},{"province_code":"u","name":"Sierra Victoria"},{"province_code":"u","name":"Sol De Mayo"},{"province_code":"u","name":"Sunica"},{"province_code":"u","name":"Talagapa"},{"province_code":"u","name":"Taquetren"},{"province_code":"u","name":"Tatuen"},{"province_code":"u","name":"Tecka"},{"province_code":"u","name":"Telsen"},{"province_code":"u","name":"Toma De Los Canales"},{"province_code":"u","name":"Toro Hosco"},{"province_code":"u","name":"Trelew"},{"province_code":"u","name":"Treorki"},{"province_code":"u","name":"Tres Picos"},{"province_code":"u","name":"Trevelin"},{"province_code":"u","name":"Uzcudun"},{"province_code":"u","name":"Valle Del Rio Chubut"},{"province_code":"u","name":"Valle Del Tecka"},{"province_code":"u","name":"Valle Frio"},{"province_code":"u","name":"Valle Garin"},{"province_code":"u","name":"Valle Hermoso"},{"province_code":"u","name":"Valle Hondo"},{"province_code":"u","name":"Valle Huemules"},{"province_code":"u","name":"Valle Los Martires"},{"province_code":"u","name":"Villa Futalaufquen"},{"province_code":"u","name":"Villa Ines"}]